{"schema_version":"canonical-root-drift-fleet-check/v1","command":"doctor","ts":"2026-05-11T03:56:05Z","status":"pass","checks":[{"name":"bash_available","status":"pass"},{"name":"jq_available","status":"pass"},{"name":"mktemp_available","status":"pass"},{"name":"sync_helper_executable","status":"pass","path":"/Users/josh/Developer/flywheel/.flywheel/scripts/sync-canonical-doctrine.sh","detail":"load-bearing — invoked per repo for drift detection"},{"name":"canonical_source_readable","status":"pass","path":"/Users/josh/Developer/flywheel/AGENTS.md","detail":"AGENTS.md baseline; warn if missing"},{"name":"audit_log_dir_writable","status":"pass","path":"/Users/josh/.local/state/flywheel"}]}
