{"schema_version":"flywheel-codex-stuck-detector-install/v1","command":"doctor","ts":"2026-05-11T05:46:17Z","status":"degraded","checks":[{"name":"launchctl_available","status":"pass"},{"name":"plutil_available","status":"pass"},{"name":"jq_available","status":"pass"},{"name":"source_plist_present","status":"fail","path":"/Users/josh/Developer/flywheel/.flywheel/launchd/ai.zeststream.flywheel-codex-stuck-detector.plist","note":"load-bearing — installer copies from .flywheel/launchd/"},{"name":"install_plist_present","status":"pass","path":"/Users/josh/Library/LaunchAgents/ai.zeststream.flywheel-codex-stuck-detector.plist"},{"name":"launchagents_dir_present","status":"pass","path":"/Users/josh/Library/LaunchAgents"},{"name":"audit_log_dir_writable","status":"pass","path":"/Users/josh/.local/state/flywheel"}]}
