{"schema_version":"dispatch-trigger-gated-precheck/v1","command":"info","name":"dispatch-trigger-gated-precheck.sh","version":"scaffolded-v0","sha256":"f661b15c3c8596f045ef243c4c4ba0a923238e79756a7fa6c20074e4d99a3950","paths":{},"env_vars":["SCAFFOLD_AUDIT_LOG"],"subcommands":["doctor","health","repair","validate","audit","why","quickstart","help","completion"],"dependencies":["bash","jq","date","shasum"],"mutation_requires":"--apply --idempotency-key (or default --json output)","canonical_cli_surfaces":["doctor","health","repair","validate","audit","why","quickstart","help","completion","--info","--schema","--examples"]}
